chatworkpy
