Metadata-Version: 2.1
Name: chatworkpy
Version: 0.0.7
Summary: chatwork module for python
Home-page: https://github.com/tys-hiroshi/chatworkpy
License: MIT # ライセンス名（省略可）
Platform: UNKNOWN
